MANIFEST.in
README.md
setup.py
lit_web.egg-info/PKG-INFO
lit_web.egg-info/SOURCES.txt
lit_web.egg-info/dependency_links.txt
lit_web.egg-info/not-zip-safe
lit_web.egg-info/requires.txt
lit_web.egg-info/top_level.txt
litweb/__init__.py
litweb/static/css/bootstrap-colorpicker.css
litweb/static/css/bootstrap-colorpicker.css.map
litweb/static/css/bootstrap-colorpicker.min.css
litweb/static/css/bootstrap-colorpicker.min.css.map
litweb/static/css/bootstrap-slider.css
litweb/static/css/bootstrap-slider.min.css
litweb/static/css/bootstrap-theme.css
litweb/static/css/bootstrap-theme.css.map
litweb/static/css/bootstrap-theme.min.css
litweb/static/css/bootstrap-theme.min.css.map
litweb/static/css/bootstrap.css
litweb/static/css/bootstrap.css.map
litweb/static/css/bootstrap.min.css
litweb/static/css/bootstrap.min.css.map
litweb/static/css/bootstrap2-toggle.min.css
litweb/static/css/layout.css
litweb/static/fonts/glyphicons-halflings-regular.eot
litweb/static/fonts/glyphicons-halflings-regular.svg
litweb/static/fonts/glyphicons-halflings-regular.ttf
litweb/static/fonts/glyphicons-halflings-regular.woff
litweb/static/fonts/glyphicons-halflings-regular.woff2
litweb/static/img/bootstrap-colorpicker/alpha-horizontal.png
litweb/static/img/bootstrap-colorpicker/alpha.png
litweb/static/img/bootstrap-colorpicker/hue-horizontal.png
litweb/static/img/bootstrap-colorpicker/hue.png
litweb/static/img/bootstrap-colorpicker/saturation.png
litweb/static/js/bootstrap-colorpicker.js
litweb/static/js/bootstrap-colorpicker.min.js
litweb/static/js/bootstrap-notify.min.js
litweb/static/js/bootstrap-slider.js
litweb/static/js/bootstrap-slider.min.js
litweb/static/js/bootstrap.js
litweb/static/js/bootstrap.min.js
litweb/static/js/bootstrap2-toggle.min.js
litweb/static/js/npm.js
litweb/static/js/script.js
litweb/templates/index.html