Metadata-Version: 1.0
Name: lit-web
Version: 0.0.1
Summary: LIT web server
Home-page: UNKNOWN
Author: UNKNOWN
Author-email: UNKNOWN
License: UNKNOWN
Platform: UNKNOWN
